pydnameth/__init__.py
pydnameth/config/__init__.py
pydnameth/config/common.py
pydnameth/config/config.py
pydnameth/config/annotations/__init__.py
pydnameth/config/annotations/annotations.py
pydnameth/config/annotations/conditions.py
pydnameth/config/annotations/subset.py
pydnameth/config/annotations/types.py
pydnameth/config/attributes/__init__.py
pydnameth/config/attributes/attributes.py
pydnameth/config/attributes/subset.py
pydnameth/config/data/__init__.py
pydnameth/config/data/data.py
pydnameth/config/data/types.py
pydnameth/config/experiment/__init__.py
pydnameth/config/experiment/experiment.py
pydnameth/config/experiment/metrics.py
pydnameth/config/experiment/params.py
pydnameth/config/experiment/types.py
pydnameth/infrastucture/__init__.py
pydnameth/infrastucture/file_name.py
pydnameth/infrastucture/path.py
pydnameth/infrastucture/load/__init__.py
pydnameth/infrastucture/load/annotations.py
pydnameth/infrastucture/load/attributes.py
pydnameth/infrastucture/load/betas.py
pydnameth/infrastucture/load/betas_adj.py
pydnameth/infrastucture/load/betas_horvath_calculator.py
pydnameth/infrastucture/load/betas_spec.py
pydnameth/infrastucture/load/cells.py
pydnameth/infrastucture/load/entropy.py
pydnameth/infrastucture/load/epimutations.py
pydnameth/infrastucture/load/excluded.py
pydnameth/infrastucture/load/genes.py
pydnameth/infrastucture/load/residuals.py
pydnameth/infrastucture/load/table.py
pydnameth/infrastucture/save/__init__.py
pydnameth/infrastucture/save/figure.py
pydnameth/infrastucture/save/info.py
pydnameth/infrastucture/save/table.py
pydnameth/model/__init__.py
pydnameth/model/context.py
pydnameth/model/tree.py
pydnameth/model/strategy/__init__.py
pydnameth/model/strategy/get.py
pydnameth/model/strategy/load.py
pydnameth/model/strategy/release.py
pydnameth/model/strategy/run.py
pydnameth/model/strategy/save.py
pydnameth/model/strategy/setup.py
pydnameth/routines/__init__.py
pydnameth/routines/common.py
pydnameth/routines/clock/__init__.py
pydnameth-0.2.4.dist-info/AUTHORS.rst
pydnameth-0.2.4.dist-info/LICENSE
pydnameth-0.2.4.dist-info/METADATA
pydnameth-0.2.4.dist-info/WHEEL
pydnameth-0.2.4.dist-info/top_level.txt
pydnameth-0.2.4.dist-info/RECORD
