Metadata-Version: 2.1
Name: pydnameth
Version: 0.2.4
Summary: DNA Methylation Analysis Package
Home-page: https://github.com/AaronBlare/pydnameth
Author: Aaron Blare
Author-email: aaron.blare@mail.ru
License: MIT license
Keywords: pydnameth
Platform: UNKNOWN
Classifier: Development Status :: 2 - Pre-Alpha
Classifier: Intended Audience :: Developers
Classifier: License :: OSI Approved :: MIT License
Classifier: Natural Language :: English
Classifier: Programming Language :: Python :: 3.6
Classifier: Programming Language :: Python :: 3.7
Requires-Dist: tqdm
Requires-Dist: numpy
Requires-Dist: statsmodels
